anvil_testcontainer/__init__.py
anvil_testcontainer/container.py
anvil_testcontainer/validation.py
anvil_testcontainer-0.1.6.dist-info/LICENSE
anvil_testcontainer-0.1.6.dist-info/METADATA
anvil_testcontainer-0.1.6.dist-info/WHEEL
anvil_testcontainer-0.1.6.dist-info/RECORD
