Metadata-Version: 2.1
Name: anvil-testcontainer
Version: 0.1.6
Summary: A secure and reusable Anvil Ethereum test container manager
License: MIT
Author: Evangelos Pappas
Author-email: epappas@evalonlabs.com
Requires-Python: >=3.12,<3.13
Classifier: License :: OSI Approved :: MIT License
Classifier: Programming Language :: Python :: 3
Classifier: Programming Language :: Python :: 3.12
Requires-Dist: docker (>=7.1.0,<8.0.0)
Requires-Dist: python-dotenv (>=1.0.0,<2.0.0)
Requires-Dist: requests (>=2.31.0,<3.0.0)
Requires-Dist: testcontainers (>=4.9.0,<5.0.0)
Requires-Dist: web3 (>=7.6.1,<8.0.0)
